<?xml version="1.0" encoding="UTF-8" standalone="no"?>
<persons>
	<person personid="0">
		<name>yjbo0</name>
		<tel>185025420</tel>
		<email>4001285@qq.com</email>
	</person>
	<person personid="1">
		<name>yjbo1</name>
		<tel>185025421</tel>
		<email>4001286@qq.com</email>
	</person>
	<person personid="2">
		<name>yjbo2</name>
		<tel>185025422</tel>
		<email>4001287@qq.com</email>
	</person>
	<person personid="3">
		<name>yjbo3</name>
		<tel>185025423</tel>
		<email>4001288@qq.com</email>
	</person>
	<person personid="4">
		<name>yjbo4</name>
		<tel>185025424</tel>
		<email>4001289@qq.com</email>
	</person>
	<person personid="5">
		<name>yjbo5</name>
		<tel>185025425</tel>
		<email>4001290@qq.com</email>
	</person>
	<person personid="6">
		<name>yjbo6</name>
		<tel>185025426</tel>
		<email>4001291@qq.com</email>
	</person>
	<person personid="7">
		<name>yjbo7</name>
		<tel>185025427</tel>
		<email>4001292@qq.com</email>
	</person>
	<person personid="8">
		<name>yjbo8</name>
		<tel>185025428</tel>
		<email>4001293@qq.com</email>
	</person>
	<person personid="9">
		<name>yjbo9</name>
		<tel>185025429</tel>
		<email>4001294@qq.com</email>
	</person>
	<person personid="10">
		<name>yjbo10</name>
		<tel>185025430</tel>
		<email>4001295@qq.com</email>
	</person>
	<person personid="11">
		<name>yjbo11</name>
		<tel>185025431</tel>
		<email>4001296@qq.com</email>
	</person>
	<person personid="12">
		<name>yjbo12</name>
		<tel>21</tel>
		<email>我修改了@qq.com</email>
	</person>
	<person personid="13">
		<name>yjbo13</name>
		<tel>185025433</tel>
		<email>4001298@qq.com</email>
	</person>
	<person personid="14">
		<name>yjbo14</name>
		<tel>185025434</tel>
		<email>4001299@qq.com</email>
	</person>
	<person personid="15">
		<name>yjbo15</name>
		<tel>185025435</tel>
		<email>4001300@qq.com</email>
	</person>
	<person personid="16">
		<name>yjbo16</name>
		<tel>185025436</tel>
		<email>4001301@qq.com</email>
	</person>
	<person personid="17">
		<name>yjbo17</name>
		<tel>185025437</tel>
		<email>4001302@qq.com</email>
	</person>
	<person personid="18">
		<name>yjbo18</name>
		<tel>185025438</tel>
		<email>4001303@qq.com</email>
	</person>
	<person personid="19">
		<name>yjbo19</name>
		<tel>185025439</tel>
		<email>4001304@qq.com</email>
	</person>
	<person personid="20">
		<name>yjbo20</name>
		<tel>185025440</tel>
		<email>4001305@qq.com</email>
	</person>
	<person personid="21">
		<name>yjbo21</name>
		<tel>185025441</tel>
		<email>4001306@qq.com</email>
	</person>
	<person personid="22">
		<name>yjbo22</name>
		<tel>185025442</tel>
		<email>4001307@qq.com</email>
	</person>
	<person personid="23">
		<name>yjbo23</name>
		<tel>185025443</tel>
		<email>4001308@qq.com</email>
	</person>
	<person personid="24">
		<name>yjbo24</name>
		<tel>185025444</tel>
		<email>4001309@qq.com</email>
	</person>
	<person personid="25">
		<name>yjbo25</name>
		<tel>185025445</tel>
		<email>4001310@qq.com</email>
	</person>
	<person personid="26">
		<name>yjbo26</name>
		<tel>185025446</tel>
		<email>4001311@qq.com</email>
	</person>
	<person personid="27">
		<name>yjbo27</name>
		<tel>185025447</tel>
		<email>4001312@qq.com</email>
	</person>
	<person personid="28">
		<name>yjbo28</name>
		<tel>185025448</tel>
		<email>4001313@qq.com</email>
	</person>
	<person personid="29">
		<name>yjbo29</name>
		<tel>185025449</tel>
		<email>4001314@qq.com</email>
	</person>
	<person personid="30">
		<name>yjbo30</name>
		<tel>185025450</tel>
		<email>4001315@qq.com</email>
	</person>
	<person personid="31">
		<name>yjbo31</name>
		<tel>185025451</tel>
		<email>4001316@qq.com</email>
	</person>
	<person personid="32">
		<name>yjbo32</name>
		<tel>185025452</tel>
		<email>4001317@qq.com</email>
	</person>
	<person personid="33">
		<name>yjbo33</name>
		<tel>185025453</tel>
		<email>4001318@qq.com</email>
	</person>
	<person personid="34">
		<name>yjbo34</name>
		<tel>185025454</tel>
		<email>4001319@qq.com</email>
	</person>
	<person personid="35">
		<name>yjbo35</name>
		<tel>185025455</tel>
		<email>4001320@qq.com</email>
	</person>
	<person personid="36">
		<name>yjbo36</name>
		<tel>185025456</tel>
		<email>4001321@qq.com</email>
	</person>
	<person personid="37">
		<name>yjbo37</name>
		<tel>185025457</tel>
		<email>4001322@qq.com</email>
	</person>
	<person personid="38">
		<name>yjbo38</name>
		<tel>185025458</tel>
		<email>4001323@qq.com</email>
	</person>
	<person personid="39">
		<name>yjbo39</name>
		<tel>185025459</tel>
		<email>4001324@qq.com</email>
	</person>
	<person personid="40">
		<name>yjbo40</name>
		<tel>185025460</tel>
		<email>4001325@qq.com</email>
	</person>
	<person personid="41">
		<name>yjbo41</name>
		<tel>185025461</tel>
		<email>4001326@qq.com</email>
	</person>
	<person personid="42">
		<name>yjbo42</name>
		<tel>185025462</tel>
		<email>4001327@qq.com</email>
	</person>
	<person personid="43">
		<name>yjbo43</name>
		<tel>185025463</tel>
		<email>4001328@qq.com</email>
	</person>
	<person personid="44">
		<name>yjbo44</name>
		<tel>185025464</tel>
		<email>4001329@qq.com</email>
	</person>
	<person personid="45">
		<name>yjbo45</name>
		<tel>185025465</tel>
		<email>4001330@qq.com</email>
	</person>
	<person personid="46">
		<name>yjbo46</name>
		<tel>185025466</tel>
		<email>4001331@qq.com</email>
	</person>
	<person personid="47">
		<name>yjbo47</name>
		<tel>185025467</tel>
		<email>4001332@qq.com</email>
	</person>
	<person personid="48">
		<name>yjbo48</name>
		<tel>185025468</tel>
		<email>4001333@qq.com</email>
	</person>
	<person personid="49">
		<name>yjbo49</name>
		<tel>185025469</tel>
		<email>4001334@qq.com</email>
	</person>
	<person personid="50">
		<name>yjbo50</name>
		<tel>185025470</tel>
		<email>4001335@qq.com</email>
	</person>
	<person personid="51">
		<name>yjbo51</name>
		<tel>185025471</tel>
		<email>4001336@qq.com</email>
	</person>
	<person personid="52">
		<name>yjbo52</name>
		<tel>185025472</tel>
		<email>4001337@qq.com</email>
	</person>
	<person personid="53">
		<name>yjbo53</name>
		<tel>185025473</tel>
		<email>4001338@qq.com</email>
	</person>
	<person personid="54">
		<name>yjbo54</name>
		<tel>185025474</tel>
		<email>4001339@qq.com</email>
	</person>
	<person personid="55">
		<name>yjbo55</name>
		<tel>185025475</tel>
		<email>4001340@qq.com</email>
	</person>
	<person personid="56">
		<name>yjbo56</name>
		<tel>185025476</tel>
		<email>4001341@qq.com</email>
	</person>
	<person personid="57">
		<name>yjbo57</name>
		<tel>185025477</tel>
		<email>4001342@qq.com</email>
	</person>
	<person personid="58">
		<name>yjbo58</name>
		<tel>185025478</tel>
		<email>4001343@qq.com</email>
	</person>
	<person personid="59">
		<name>yjbo59</name>
		<tel>185025479</tel>
		<email>4001344@qq.com</email>
	</person>
	<person personid="60">
		<name>yjbo60</name>
		<tel>185025480</tel>
		<email>4001345@qq.com</email>
	</person>
	<person personid="61">
		<name>yjbo61</name>
		<tel>185025481</tel>
		<email>4001346@qq.com</email>
	</person>
	<person personid="62">
		<name>yjbo62</name>
		<tel>185025482</tel>
		<email>4001347@qq.com</email>
	</person>
	<person personid="63">
		<name>yjbo63</name>
		<tel>185025483</tel>
		<email>4001348@qq.com</email>
	</person>
	<person personid="64">
		<name>yjbo64</name>
		<tel>185025484</tel>
		<email>4001349@qq.com</email>
	</person>
	<person personid="65">
		<name>yjbo65</name>
		<tel>185025485</tel>
		<email>4001350@qq.com</email>
	</person>
	<person personid="66">
		<name>yjbo66</name>
		<tel>185025486</tel>
		<email>4001351@qq.com</email>
	</person>
	<person personid="67">
		<name>yjbo67</name>
		<tel>185025487</tel>
		<email>4001352@qq.com</email>
	</person>
	<person personid="68">
		<name>yjbo68</name>
		<tel>185025488</tel>
		<email>4001353@qq.com</email>
	</person>
	<person personid="69">
		<name>yjbo69</name>
		<tel>185025489</tel>
		<email>4001354@qq.com</email>
	</person>
	<person personid="70">
		<name>yjbo70</name>
		<tel>185025490</tel>
		<email>4001355@qq.com</email>
	</person>
	<person personid="71">
		<name>yjbo71</name>
		<tel>185025491</tel>
		<email>4001356@qq.com</email>
	</person>
	<person personid="72">
		<name>yjbo72</name>
		<tel>185025492</tel>
		<email>4001357@qq.com</email>
	</person>
	<person personid="73">
		<name>yjbo73</name>
		<tel>185025493</tel>
		<email>4001358@qq.com</email>
	</person>
	<person personid="74">
		<name>yjbo74</name>
		<tel>185025494</tel>
		<email>4001359@qq.com</email>
	</person>
	<person personid="75">
		<name>yjbo75</name>
		<tel>185025495</tel>
		<email>4001360@qq.com</email>
	</person>
	<person personid="76">
		<name>yjbo76</name>
		<tel>185025496</tel>
		<email>4001361@qq.com</email>
	</person>
	<person personid="77">
		<name>yjbo77</name>
		<tel>185025497</tel>
		<email>4001362@qq.com</email>
	</person>
	<person personid="78">
		<name>yjbo78</name>
		<tel>185025498</tel>
		<email>4001363@qq.com</email>
	</person>
	<person personid="79">
		<name>yjbo79</name>
		<tel>185025499</tel>
		<email>4001364@qq.com</email>
	</person>
	<person personid="80">
		<name>yjbo80</name>
		<tel>185025500</tel>
		<email>4001365@qq.com</email>
	</person>
	<person personid="81">
		<name>yjbo81</name>
		<tel>185025501</tel>
		<email>4001366@qq.com</email>
	</person>
	<person personid="82">
		<name>yjbo82</name>
		<tel>185025502</tel>
		<email>4001367@qq.com</email>
	</person>
	<person personid="83">
		<name>yjbo83</name>
		<tel>185025503</tel>
		<email>4001368@qq.com</email>
	</person>
	<person personid="84">
		<name>yjbo84</name>
		<tel>185025504</tel>
		<email>4001369@qq.com</email>
	</person>
	<person personid="85">
		<name>yjbo85</name>
		<tel>185025505</tel>
		<email>4001370@qq.com</email>
	</person>
	<person personid="86">
		<name>yjbo86</name>
		<tel>185025506</tel>
		<email>4001371@qq.com</email>
	</person>
	<person personid="87">
		<name>yjbo87</name>
		<tel>185025507</tel>
		<email>4001372@qq.com</email>
	</person>
	<person personid="88">
		<name>yjbo88</name>
		<tel>185025508</tel>
		<email>4001373@qq.com</email>
	</person>
	<person personid="89">
		<name>yjbo89</name>
		<tel>185025509</tel>
		<email>4001374@qq.com</email>
	</person>
	<person personid="90">
		<name>yjbo90</name>
		<tel>185025510</tel>
		<email>4001375@qq.com</email>
	</person>
	<person personid="91">
		<name>yjbo91</name>
		<tel>185025511</tel>
		<email>4001376@qq.com</email>
	</person>
	<person personid="92">
		<name>yjbo92</name>
		<tel>185025512</tel>
		<email>4001377@qq.com</email>
	</person>
	<person personid="93">
		<name>yjbo93</name>
		<tel>185025513</tel>
		<email>4001378@qq.com</email>
	</person>
	<person personid="94">
		<name>yjbo94</name>
		<tel>185025514</tel>
		<email>4001379@qq.com</email>
	</person>
	<person personid="95">
		<name>yjbo95</name>
		<tel>185025515</tel>
		<email>4001380@qq.com</email>
	</person>
	<person personid="96">
		<name>yjbo96</name>
		<tel>185025516</tel>
		<email>4001381@qq.com</email>
	</person>
	<person personid="97">
		<name>yjbo97</name>
		<tel>185025517</tel>
		<email>4001382@qq.com</email>
	</person>
	<person personid="98">
		<name>yjbo98</name>
		<tel>185025518</tel>
		<email>4001383@qq.com</email>
	</person>
	<person personid="99">
		<name>yjbo99</name>
		<tel>185025519</tel>
		<email>4001384@qq.com</email>
	</person>
</persons>